{
  "openapi": "3.1.0",
  "info": {
    "title": "IMDC API",
    "version": "1.0.0",
    "description": "OpenAPI 3.1 specification for IMDC core endpoints."
  },
  "servers": [
    { "url": "http://localhost/api", "description": "Local" }
  ],
  "paths": {
    "/health": {
      "get": {
        "summary": "Health check",
        "responses": {
          "200": {
            "description": "OK",
            "content": {
              "application/json": {
                "schema": { "$ref": "#/components/schemas/ApiSuccess" }
              }
            }
          }
        }
      }
    },
    "/rbac/roles": {
      "get": {
        "summary": "List roles",
        "responses": {
          "200": {
            "description": "Roles",
            "content": {
              "application/json": {
                "schema": { "$ref": "#/components/schemas/ApiSuccess" }
              }
            }
          }
        }
      }
    },
    "/rbac/users/{userId}/roles/{roleId}": {
      "post": {
        "summary": "Attach role to user",
        "parameters": [
          { "name": "userId", "in": "path", "required": true, "schema": { "type": "integer" } },
          { "name": "roleId", "in": "path", "required": true, "schema": { "type": "integer" } }
        ],
        "responses": {
          "200": { "description": "Attached", "content": { "application/json": { "schema": { "$ref": "#/components/schemas/ApiSuccess" } } } },
          "404": { "description": "Not Found", "content": { "application/json": { "schema": { "$ref": "#/components/schemas/ApiError" } } } }
        }
      }
    },
    "/social/posts": {
      "get": {
        "summary": "List posts",
        "parameters": [
          { "name": "page", "in": "query", "schema": { "type": "integer", "minimum": 1 } },
          { "name": "per_page", "in": "query", "schema": { "type": "integer", "minimum": 1, "maximum": 100 } }
        ],
        "responses": {
          "200": { "description": "List", "content": { "application/json": { "schema": { "$ref": "#/components/schemas/ApiSuccess" } } } }
        }
      },
      "post": {
        "summary": "Create post",
        "requestBody": {
          "required": true,
          "content": {
            "application/json": {
              "schema": {
                "type": "object",
                "required": ["title","user_id"],
                "properties": {
                  "title": { "type": "string" },
                  "summary": { "type": "string" },
                  "content": { "type": "string" },
                  "user_id": { "type": "integer" },
                  "status": { "type": "string", "enum": ["draft","published","archived"] }
                }
              }
            }
          }
        },
        "responses": {
          "201": { "description": "Created", "content": { "application/json": { "schema": { "$ref": "#/components/schemas/ApiSuccess" } } } },
          "422": { "description": "Validation error", "content": { "application/json": { "schema": { "$ref": "#/components/schemas/ApiError" } } } }
        }
      }
    },
    "/social/messages": {
      "get": {
        "summary": "List messages",
        "parameters": [
          { "name": "sender_id", "in": "query", "schema": { "type": "integer" } },
          { "name": "receiver_id", "in": "query", "schema": { "type": "integer" } },
          { "name": "safe_room_id", "in": "query", "schema": { "type": "integer" } }
        ],
        "responses": { "200": { "description": "List", "content": { "application/json": { "schema": { "$ref": "#/components/schemas/ApiSuccess" } } } } }
      },
      "post": {
        "summary": "Send message",
        "requestBody": {
          "required": true,
          "content": {
            "application/json": {
              "schema": {
                "type": "object",
                "required": ["sender_id","body"],
                "properties": {
                  "sender_id": { "type": "integer" },
                  "receiver_id": { "type": "integer", "nullable": true },
                  "safe_room_id": { "type": "integer", "nullable": true },
                  "body": { "type": "string" }
                }
              }
            }
          }
        },
        "responses": {
          "201": { "description": "Created", "content": { "application/json": { "schema": { "$ref": "#/components/schemas/ApiSuccess" } } } },
          "422": { "description": "Validation error", "content": { "application/json": { "schema": { "$ref": "#/components/schemas/ApiError" } } } }
        }
      }
    },
    "/social/messages/{id}": {
      "delete": {
        "summary": "Delete message",
        "parameters": [
          { "name": "id", "in": "path", "required": true, "schema": { "type": "integer" } }
        ],
        "responses": {
          "200": { "description": "Deleted", "content": { "application/json": { "schema": { "$ref": "#/components/schemas/ApiSuccess" } } } },
          "404": { "description": "Not Found", "content": { "application/json": { "schema": { "$ref": "#/components/schemas/ApiError" } } } }
        }
      }
    },
    "/social/safe-rooms": {
      "get": { "summary": "List safe rooms", "responses": { "200": { "description": "OK", "content": { "application/json": { "schema": { "$ref": "#/components/schemas/ApiSuccess" } } } } } },
      "post": {
        "summary": "Create safe room",
        "requestBody": {
          "required": true,
          "content": { "application/json": { "schema": { "type": "object", "required": ["name"], "properties": { "name": { "type": "string" }, "panic_code": { "type": "string" } } } } }
        },
        "responses": { "201": { "description": "Created", "content": { "application/json": { "schema": { "$ref": "#/components/schemas/ApiSuccess" } } } } }
      }
    },
    "/social/safe-rooms/{id}/panic": {
      "patch": {
        "summary": "Set panic code",
        "parameters": [
          { "name": "id", "in": "path", "required": true, "schema": { "type": "integer" } }
        ],
        "requestBody": {
          "required": true,
          "content": { "application/json": { "schema": { "type": "object", "required": ["panic_code"], "properties": { "panic_code": { "type": "string" } } } } }
        },
        "responses": { "200": { "description": "Updated", "content": { "application/json": { "schema": { "$ref": "#/components/schemas/ApiSuccess" } } } } }
      }
    },
    "/market/shops": {
      "get": { "summary": "List shops", "responses": { "200": { "description": "OK", "content": { "application/json": { "schema": { "$ref": "#/components/schemas/ApiSuccess" } } } } } },
      "post": {
        "summary": "Create shop",
        "requestBody": {
          "required": true,
          "content": { "application/json": { "schema": { "type": "object", "required": ["name","owner_id"], "properties": { "name": { "type": "string" }, "owner_id": { "type": "integer" } } } } }
        },
        "responses": { "201": { "description": "Created", "content": { "application/json": { "schema": { "$ref": "#/components/schemas/ApiSuccess" } } } } }
      }
    },
    "/market/products": {
      "get": {
        "summary": "List products",
        "parameters": [
          { "name": "shop_id", "in": "query", "schema": { "type": "integer" } },
          { "name": "search", "in": "query", "schema": { "type": "string" } },
          { "name": "per_page", "in": "query", "schema": { "type": "integer", "minimum": 1, "maximum": 100 } }
        ],
        "responses": { "200": { "description": "OK", "content": { "application/json": { "schema": { "$ref": "#/components/schemas/ApiSuccess" } } } } }
      },
      "post": {
        "summary": "Create product",
        "requestBody": {
          "required": true,
          "content": { "application/json": { "schema": { "$ref": "#/components/schemas/ProductCreate" } } }
        },
        "responses": { "201": { "description": "Created", "content": { "application/json": { "schema": { "$ref": "#/components/schemas/ApiSuccess" } } } } }
      }
    },
    "/market/products/{id}": {
      "patch": {
        "summary": "Update product",
        "parameters": [
          { "name": "id", "in": "path", "required": true, "schema": { "type": "integer" } }
        ],
        "requestBody": {
          "required": true,
          "content": { "application/json": { "schema": { "type": "object", "properties": { "name": { "type": "string" }, "price": { "type": "integer", "minimum": 0 }, "meta": { "type": "object" } } } } }
        },
        "responses": { "200": { "description": "Updated", "content": { "application/json": { "schema": { "$ref": "#/components/schemas/ApiSuccess" } } } } }
      },
      "delete": {
        "summary": "Delete product",
        "parameters": [
          { "name": "id", "in": "path", "required": true, "schema": { "type": "integer" } }
        ],
        "responses": {
          "200": { "description": "Deleted", "content": { "application/json": { "schema": { "$ref": "#/components/schemas/ApiSuccess" } } } },
          "404": { "description": "Not Found", "content": { "application/json": { "schema": { "$ref": "#/components/schemas/ApiError" } } } }
        }
      }
    },
    "/market/inventory/{productId}/adjust": {
      "post": {
        "summary": "Adjust inventory",
        "parameters": [
          { "name": "productId", "in": "path", "required": true, "schema": { "type": "integer" } }
        ],
        "requestBody": {
          "required": true,
          "content": { "application/json": { "schema": { "type": "object", "required": ["delta"], "properties": { "delta": { "type": "integer" } } } } }
        },
        "responses": {
          "200": { "description": "Adjusted", "content": { "application/json": { "schema": { "$ref": "#/components/schemas/ApiSuccess" } } } },
          "422": { "description": "Invalid", "content": { "application/json": { "schema": { "$ref": "#/components/schemas/ApiError" } } } }
        }
      }
    },
    "/market/orders": {
      "get": {
        "summary": "List orders",
        "parameters": [
          { "name": "user_id", "in": "query", "schema": { "type": "integer" } },
          { "name": "status", "in": "query", "schema": { "type": "string" } }
        ],
        "responses": { "200": { "description": "OK", "content": { "application/json": { "schema": { "$ref": "#/components/schemas/ApiSuccess" } } } } }
      },
      "post": {
        "summary": "Create order",
        "requestBody": {
          "required": true,
          "content": { "application/json": { "schema": { "type": "object", "required": ["user_id"], "properties": { "user_id": { "type": "integer" } } } } }
        },
        "responses": { "201": { "description": "Created", "content": { "application/json": { "schema": { "$ref": "#/components/schemas/ApiSuccess" } } } } }
      }
    },
    "/market/orders/{orderId}/items": {
      "post": {
        "summary": "Add item to order",
        "parameters": [
          { "name": "orderId", "in": "path", "required": true, "schema": { "type": "integer" } }
        ],
        "requestBody": {
          "required": true,
          "content": { "application/json": { "schema": { "type": "object", "required": ["product_id","qty"], "properties": { "product_id": { "type": "integer" }, "qty": { "type": "integer", "minimum": 1 }, "price": { "type": "integer", "minimum": 0 } } } } }
        },
        "responses": {
          "200": { "description": "OK", "content": { "application/json": { "schema": { "$ref": "#/components/schemas/ApiSuccess" } } } },
          "404": { "description": "Order not found", "content": { "application/json": { "schema": { "$ref": "#/components/schemas/ApiError" } } } }
        }
      }
    },
    "/market/orders/{orderId}/status": {
      "patch": {
        "summary": "Set order status",
        "parameters": [
          { "name": "orderId", "in": "path", "required": true, "schema": { "type": "integer" } }
        ],
        "requestBody": {
          "required": true,
          "content": { "application/json": { "schema": { "type": "object", "required": ["status"], "properties": { "status": { "type": "string", "enum": ["pending","paid","shipped","cancelled","refunded"] } } } } }
        },
        "responses": { "200": { "description": "Updated", "content": { "application/json": { "schema": { "$ref": "#/components/schemas/ApiSuccess" } } } } }
      }
    }
  },
  "components": {
    "schemas": {
      "ApiSuccess": {
        "type": "object",
        "properties": {
          "success": { "type": "boolean", "const": true },
          "data": {},
          "trace_id": { "type": "string" }
        },
        "required": ["success","trace_id"]
      },
      "ApiError": {
        "type": "object",
        "properties": {
          "success": { "type": "boolean", "const": false },
          "error": { "type": "string" },
          "trace_id": { "type": "string" }
        },
        "required": ["success","error","trace_id"]
      },
      "ProductCreate": {
        "type": "object",
        "required": ["shop_id","name","sku","price"],
        "properties": {
          "shop_id": { "type": "integer" },
          "name": { "type": "string" },
          "sku": { "type": "string" },
          "price": { "type": "integer", "minimum": 0 },
          "meta": { "type": "object" }
        }
      }
    }
  }
}
